Metadata-Version: 2.4
Name: fraocme
Version: 1.0.0b1
Summary: A compact, testable framework for writing Advent of Code solutions in Python
Author-email: MalikAza <dakota.froissart@powaza.fr>, Weyrd <pierre.pinateau@gmail.com>
License: MIT
Project-URL: Homepage, https://github.com/MalikAza/fraocme
Project-URL: Repository, https://github.com/MalikAza/fraocme.git
Project-URL: Issues, https://github.com/MalikAza/fraocme/issues
Project-URL: Documentation, https://github.com/MalikAza/fraocme#readme
Keywords: advent-of-code,aoc,framework,python,testing
Classifier: Development Status :: 3 - Alpha
Classifier: Intended Audience :: Developers
Classifier: License :: OSI Approved :: MIT License
Classifier: Programming Language :: Python :: 3
Classifier: Programming Language :: Python :: 3.13
Classifier: Topic :: Software Development :: Libraries :: Python Modules
Classifier: Topic :: Games/Entertainment :: Puzzle Games
Requires-Python: >=3.13
License-File: LICENSE
Provides-Extra: dev
Requires-Dist: pytest>=7.0; extra == "dev"
Requires-Dist: pytest-cov>=4.0; extra == "dev"
Requires-Dist: ruff>=0.1.0; extra == "dev"
Dynamic: license-file
